qemu/__init__.py
qemu-0.0.0a1.dist-info/METADATA
qemu-0.0.0a1.dist-info/WHEEL
qemu-0.0.0a1.dist-info/top_level.txt
qemu-0.0.0a1.dist-info/RECORD
