Metadata-Version: 2.1
Name: qemu
Version: 0.0.0a1
Summary: QEMU Python Build, Debug and SDK tooling.
Home-page: https://www.qemu.org/
Maintainer: John Snow
Maintainer-email: qemu-devel@nongnu.org
License: UNKNOWN
Download-URL: https://www.qemu.org/download/
Platform: UNKNOWN
Classifier: Development Status :: 5 - Production/Stable
Classifier: License :: OSI Approved :: GNU General Public License v2 (GPLv2)
Classifier: Natural Language :: English
Classifier: Operating System :: OS Independent
Requires-Python: >=3.5
